dsolver/__init__.py
dsolver/__main__.py
dsolver/executor.py
dsolver/mylog.py
dsolver/processor.py
dsolver/report.py
dsolver-0.0.1.dist-info/LICENSE
dsolver-0.0.1.dist-info/METADATA
dsolver-0.0.1.dist-info/WHEEL
dsolver-0.0.1.dist-info/top_level.txt
dsolver-0.0.1.dist-info/RECORD
