Metadata-Version: 2.1
Name: dsolver
Version: 0.0.1
Summary: Resolve Python dependencies automatically
Home-page: https://github.com/shivampip/DSolver
Author: Shivam Agrawal
Author-email: shivam301296@gmail.com
License: UNKNOWN
Platform: UNKNOWN
Classifier: Programming Language :: Python :: 3
Classifier: License :: OSI Approved :: MIT License
Classifier: Operating System :: OS Independent
